secstache.py
secstache-0.3.7.dist-info/entry_points.txt
secstache-0.3.7.dist-info/WHEEL
secstache-0.3.7.dist-info/METADATA
secstache-0.3.7.dist-info/RECORD
