Metadata-Version: 2.1
Name: secstache
Version: 0.3.7
Summary: Fill mustache template(s) with secrets from secret store(s).
Home-page: https://github.com/9horses/secstache
License: MIT
Author: Shinichi Urano
Requires-Python: >=3.8,<4.0
Classifier: License :: OSI Approved :: MIT License
Classifier: Programming Language :: Python :: 3
Classifier: Programming Language :: Python :: 3.10
Classifier: Programming Language :: Python :: 3.8
Classifier: Programming Language :: Python :: 3.9
Requires-Dist: argparse (>=1.4.0,<2.0.0)
Requires-Dist: boto3 (>=1.21.37,<2.0.0)
Requires-Dist: pystache (>=0.6.0,<0.7.0)
Project-URL: Repository, https://github.com/9horses/secstache
